Metadata-Version: 2.1
Name: django-admin-item-owner
Version: 0.2.0
Summary: Model item always has an owner, and login user can only see owned items.
Home-page: UNKNOWN
Author: zencore
Author-email: dobetter@zencore.cn
License: MIT
Keywords: django-admin-item-owner
Platform: UNKNOWN
Classifier: Development Status :: 5 - Production/Stable
Classifier: Intended Audience :: Developers
Classifier: Topic :: Software Development :: Libraries :: Python Modules
Classifier: License :: OSI Approved :: MIT License
Classifier: Programming Language :: Python :: 3
Classifier: Programming Language :: Python :: 3 :: Only
Requires: django
Requires: django_middleware_global_request
